get_avg_laba4_9/__init__.py
get_avg_laba4_9/main.py
get_avg_laba4_9-0.1.0.dist-info/METADATA
get_avg_laba4_9-0.1.0.dist-info/WHEEL
get_avg_laba4_9-0.1.0.dist-info/licenses/LICENSE
get_avg_laba4_9-0.1.0.dist-info/RECORD
